{
	"configurations" : 
	[
		{
			"directories" : 
			[
				{
					"build" : ".",
					"jsonFile" : "directory-.-Debug-f5ebdc15457944623624.json",
					"minimumCMakeVersion" : 
					{
						"string" : "3.25"
					},
					"projectIndex" : 0,
					"source" : ".",
					"targetIndexes" : 
					[
						0
					]
				}
			],
			"name" : "Debug",
			"projects" : 
			[
				{
					"directoryIndexes" : 
					[
						0
					],
					"name" : "SudokuAbgabe",
					"targetIndexes" : 
					[
						0
					]
				}
			],
			"targets" : 
			[
				{
					"directoryIndex" : 0,
					"id" : "SudokuAbgabe::@6890427a1f51a3e7e1df",
					"jsonFile" : "target-SudokuAbgabe-Debug-c9fa353409b3753e741b.json",
					"name" : "SudokuAbgabe",
					"projectIndex" : 0
				}
			]
		}
	],
	"kind" : "codemodel",
	"paths" : 
	{
		"build" : "/tank/home/21bade1bif/SudokuAbgabe/cmake-build-debug",
		"source" : "/tank/home/21bade1bif/SudokuAbgabe"
	},
	"version" : 
	{
		"major" : 2,
		"minor" : 4
	}
}
